un_locc/AtkinsonHyperlegible-Regular.ttf
un_locc/__init__.py
un_locc/un_locc.py
un_locc-0.1.9.dist-info/METADATA
un_locc-0.1.9.dist-info/WHEEL
un_locc-0.1.9.dist-info/licenses/LICENSE
un_locc-0.1.9.dist-info/RECORD
