Metadata-Version: 2.4
Name: un-locc
Version: 0.1.9
Summary: Universal Lossy Optical Context Compression for Vision-Language Models
Project-URL: Homepage, https://github.com/MaxDevv/Un-LOCC
Project-URL: Documentation, https://github.com/MaxDevv/Un-LOCC#readme
Project-URL: Repository, https://github.com/MaxDevv/Un-LOCC
Project-URL: Issues, https://github.com/MaxDevv/Un-LOCC/issues
Project-URL: Changelog, https://github.com/MaxDevv/Un-LOCC/blob/main/CHANGELOG.md
Author-email: MaxDevv <maxdevv@example.com>
Maintainer-email: MaxDevv <maxdevv@example.com>
License-Expression: MIT
License-File: LICENSE
Keywords: compression,context-compression,openai,optical,vlm
Classifier: Development Status :: 4 - Beta
Classifier: Intended Audience :: Developers
Classifier: License :: OSI Approved :: MIT License
Classifier: Operating System :: OS Independent
Classifier: Programming Language :: Python :: 3
Classifier: Programming Language :: Python :: 3.8
Classifier: Programming Language :: Python :: 3.9
Classifier: Programming Language :: Python :: 3.10
Classifier: Programming Language :: Python :: 3.11
Classifier: Programming Language :: Python :: 3.12
Classifier: Topic :: Scientific/Engineering :: Artificial Intelligence
Classifier: Topic :: Software Development :: Libraries :: Python Modules
Requires-Python: >=3.8
Requires-Dist: openai>=1.0.0
Requires-Dist: pillow>=8.0.0
Requires-Dist: pypdfium2>=4.0.0
Requires-Dist: reportlab>=4.0.0
